funfedi_parsing_test_cases/__init__.py
funfedi_parsing_test_cases/__main__.py
funfedi_parsing_test_cases/test_cases.py
funfedi_parsing_test_cases/test_types.py
funfedi_parsing_test_cases/testing.py
funfedi_parsing_test_cases/types.py
funfedi_parsing_test_cases/version.py
funfedi_parsing_test_cases/activity/__init__.py
funfedi_parsing_test_cases/activity/addressing.py
funfedi_parsing_test_cases/activity/create.py
funfedi_parsing_test_cases/activity/test_addressing.py
funfedi_parsing_test_cases/cases/__init__.py
funfedi_parsing_test_cases/cases/activity.py
funfedi_parsing_test_cases/cases/test_activity.py
funfedi_parsing_test_cases/schema/__init__.py
funfedi_parsing_test_cases/schema/activity_pub_activity.schema.json
funfedi_parsing_test_cases/schema/test_init.py
funfedi_parsing_test_cases/suite/__init__.py
funfedi_parsing_test_cases/suite/generate_doc.py
funfedi_parsing_test_cases/suite/test_generate_doc.py
funfedi_parsing_test_cases/suite/test_suite.py
funfedi_parsing_test_cases/suite/test_validators.py
funfedi_parsing_test_cases/suite/validators.py
funfedi_parsing_test_cases-0.1.2.dist-info/METADATA
funfedi_parsing_test_cases-0.1.2.dist-info/WHEEL
funfedi_parsing_test_cases-0.1.2.dist-info/RECORD
