Metadata-Version: 2.4
Name: funfedi_parsing_test_cases
Version: 0.1.2
Project-URL: repository, https://codeberg.org/funfedidev/funfedi_parsing_test_cases
Requires-Python: >=3.11
Requires-Dist: bovine>=0.5.19
Requires-Dist: jsonschema>=4.25.1
